instascrape/__init__.py
instascrape/__main__.py
instascrape/constants.py
instascrape/exceptions.py
instascrape/group.py
instascrape/instascrape.py
instascrape/structures.py
instascrape/utils.py
instascrape/commands/__init__.py
instascrape/commands/cookies.py
instascrape/commands/download.py
instascrape/commands/dump.py
instascrape/commands/login.py
instascrape/commands/logout.py
instascrape/commands/whoami.py
instascraper-2.0.4.dist-info/LICENSE.txt
instascraper-2.0.4.dist-info/METADATA
instascraper-2.0.4.dist-info/WHEEL
instascraper-2.0.4.dist-info/entry_points.txt
instascraper-2.0.4.dist-info/top_level.txt
instascraper-2.0.4.dist-info/RECORD
