Metadata-Version: 2.1
Name: instascraper
Version: 2.0.4
Summary: A fast and lightweight Instagram media downloader.
Home-page: https://github.com/tnychn/instascrape
Author: tnychn
Author-email: tonychan2342@gmail.com
License: MIT
Keywords: instagram,scraper,downloader,media,api,cli
Platform: UNKNOWN
Requires-Python: >=3.6.0
Requires-Dist: requests
Requires-Dist: tqdm
Requires-Dist: colorama
